pysolate/__init__.py
pysolate/cli.py
pysolate/container.py
pysolate_container-0.2.dist-info/METADATA
pysolate_container-0.2.dist-info/WHEEL
pysolate_container-0.2.dist-info/entry_points.txt
pysolate_container-0.2.dist-info/top_level.txt
pysolate_container-0.2.dist-info/RECORD
