Metadata-Version: 2.1
Name: pysolate-container
Version: 0.2
Summary: UNKNOWN
Home-page: UNKNOWN
Author: Keane O'Kelley
Author-email: keane.m.okelley@gmail.com
License: MIT
Platform: UNKNOWN
Requires-Dist: colorful
